anu_module/__init__.py
anu_module/core.py
anushka_module-1.0.0.dist-info/METADATA
anushka_module-1.0.0.dist-info/WHEEL
anushka_module-1.0.0.dist-info/top_level.txt
anushka_module-1.0.0.dist-info/RECORD
