Metadata-Version: 2.4
Name: anushka-module
Version: 1.0.0
Summary: My first pip installable module
Author: Anushka
